investimentpy_dridev-1.0.2.dist-info/licenses/LICENSE
investpy/__init__.py
investpy/calculos.py
investpy/dados.py
investpy/visualizacao.py
investimentpy_dridev-1.0.2.dist-info/METADATA
investimentpy_dridev-1.0.2.dist-info/WHEEL
investimentpy_dridev-1.0.2.dist-info/top_level.txt
investimentpy_dridev-1.0.2.dist-info/RECORD
