Metadata-Version: 2.4
Name: investimentpy-dridev
Version: 1.0.2
Summary: Uma biblioteca para análise de investimentos
Home-page: https://github.com/drielDev/InvestPy
Author: Adriel Roque
Author-email: adrielroquedev@gmail.com
License: MIT
License-File: LICENSE
Dynamic: author
Dynamic: author-email
Dynamic: description
Dynamic: description-content-type
Dynamic: home-page
Dynamic: license
Dynamic: license-file
Dynamic: summary
